ruamelmod/__init__.py
ruamel.std.encryptedzip-1.0.1.dist-info/METADATA
ruamel.std.encryptedzip-1.0.1.dist-info/WHEEL
ruamel.std.encryptedzip-1.0.1.dist-info/top_level.txt
ruamel.std.encryptedzip-1.0.1.dist-info/RECORD
