Metadata-Version: 2.1
Name: ruamel.std.encryptedzip
Version: 1.0.1
Summary: Modified version of ruamel.std.zipfile that adds support for encrypted zip archives.
Home-page: https://github.com/projectintel-anon/ruamelmod
Author: The Enigma Project
Author-email: theenigmaproject@cyberservices.com
License: MIT
Platform: UNKNOWN
Classifier: License :: OSI Approved :: MIT License
Classifier: Programming Language :: Python :: 3
Classifier: Programming Language :: Python :: 3.9
